leetcli/main.py
leetcli/auth/user.py
leetcli/problems/problem.py
leetcli/problems/status_code.py
leetcli/utils/file.py
leetcli/utils/language.py
leetcli/utils/query.py
leetcli/utils/req.py
leetcli/utils/variable.py
local_leetcode-0.1.0.dist-info/licenses/LICENSE
local_leetcode-0.1.0.dist-info/METADATA
local_leetcode-0.1.0.dist-info/WHEEL
local_leetcode-0.1.0.dist-info/entry_points.txt
local_leetcode-0.1.0.dist-info/top_level.txt
local_leetcode-0.1.0.dist-info/RECORD
