Metadata-Version: 2.4
Name: local-leetcode
Version: 0.1.0
Summary: LeetCode CLI tool to browse and solve problems from the terminal
Author-email: Lee Hajun <wklee610@gmail.com>
License: MIT
Project-URL: Homepage, https://github.com/wklee610/leetcode-cli
Project-URL: Repository, https://github.com/wklee610/leetcode-cli
Project-URL: Issues, https://github.com/wklee610/leetcode-cli/issues
Requires-Python: >=3.9
License-File: LICENSE
Requires-Dist: click>=8.0
Requires-Dist: requests>=2.28
Requires-Dist: browser-cookie3>=0.17.1
Requires-Dist: tabulate>=0.9.0
Requires-Dist: beautifulsoup4>=4.12.0
Dynamic: license-file
